.coveragerc
.pre-commit-config.yaml
AUTHORS.md
CHANGELOG.md
LICENSE.md
README.md
kw/__init__.py
kw/platform/__init__.py
kw/platform/_compat.py
kw/platform/aiohttp/__init__.py
kw/platform/aiohttp/middlewares.py
kw/platform/aiohttp/monkey.py
kw/platform/aiohttp/session.py
kw/platform/aiohttp/utils.py
kw/platform/monkey.py
kw/platform/requests/__init__.py
kw/platform/requests/monkey.py
kw/platform/requests/session.py
kw/platform/settings.py
kw/platform/utils.py
kw/platform/wrappers.py
kw/platform/wsgi.py
pyproject.toml
tox.ini
kiwi_platform-0.3.0.dist-info/LICENSE.md
kiwi_platform-0.3.0.dist-info/WHEEL
kiwi_platform-0.3.0.dist-info/METADATA
kiwi_platform-0.3.0.dist-info/RECORD
