Metadata-Version: 2.1
Name: kiwi-platform
Version: 0.3.0
Summary: Company standards as code for Kiwi.com
Home-page: https://github.com/kiwicom/kiwi-platform-py/
Keywords: kiwicom
Author: Bence Nagy
Author-email: bence@kiwi.com
Requires-Python: >=2.7, !=3.0.*, !=3.1.*, !=3.2.*, !=3.3.*, !=3.4.*
Classifier: Development Status :: 1 - Planning
Classifier: Intended Audience :: Developers
Classifier: Operating System :: OS Independent
Classifier: Programming Language :: Python
Classifier: Programming Language :: Python :: 2
Classifier: Programming Language :: Python :: 2.7
Classifier: Programming Language :: Python :: 3
Classifier: Programming Language :: Python :: 3.5
Classifier: Programming Language :: Python :: 3.6
Classifier: Programming Language :: Python :: 3.7
Classifier: Programming Language :: Python :: 3.8
Classifier: Programming Language :: Python :: Implementation :: CPython
Classifier: Topic :: Internet :: WWW/HTTP :: Dynamic Content
Classifier: Topic :: Software Development :: Libraries :: Python Modules
Provides-Extra: aiohttp
Provides-Extra: docs
Requires-Dist: aiohttp (>=3.5,<4.0); (python_version >= "3.5.3" and python_version < "4.0.0") and (extra == "aiohttp")
Requires-Dist: python-dateutil (>=2.8.1,<3.0.0)
Requires-Dist: sphinx (>=2.1,<3.0); (python_version >= "3.5.3" and python_version < "4.0.0") and (extra == "docs")
Requires-Dist: webob (>=1.8,<2.0)
Requires-Dist: wrapt (>=1.11,<2.0)
Project-URL: Repository, https://github.com/kiwicom/kiwi-platform-py/
